{"num":"037","x":null,"y":null,"or":[{"location":"Mt. Pyre - Outside","method":"Walking / Grass","rarity":"15%","minlevel":"29","maxlevel":"31"},{"location":"Mt. Pyre - Outside","method":"Horde","rarity":"5%","minlevel":"15","maxlevel":"15"},{"location":"Mt. Pyre - Summit","method":"Walking / Grass","rarity":"15%","minlevel":"29","maxlevel":"31"},{"location":"Mt. Pyre - Summit","method":"Horde","rarity":"5%","minlevel":"15","maxlevel":"15"},{"location":"Mirage Forest - North of Route 124","method":"Walking / Grass","rarity":"10%","minlevel":"36","maxlevel":"38"}],"as":[{"location":"Mt. Pyre - Outside","method":"Walking / Grass","rarity":"15%","minlevel":"29","maxlevel":"31"},{"location":"Mt. Pyre - Outside","method":"Horde","rarity":"5%","minlevel":"15","maxlevel":"15"},{"location":"Mt. Pyre - Summit","method":"Walking / Grass","rarity":"15%","minlevel":"29","maxlevel":"31"},{"location":"Mt. Pyre - Summit","method":"Horde","rarity":"5%","minlevel":"15","maxlevel":"15"},{"location":"Mirage Forest - North of Route 124","method":"Walking / Grass","rarity":"10%","minlevel":"36","maxlevel":"38"}]}
