{"num":"599","x":null,"y":null,"or":[{"location":"Mirage Cave - North of Fortree","method":"Walking / Grass","rarity":"30%","minlevel":"36","maxlevel":"38"},{"location":"Mirage Cave - North of Route 124","method":"Walking / Grass","rarity":"60%","minlevel":"36","maxlevel":"38"},{"location":"Mirage Cave - West of Rustboro","method":"Walking / Grass","rarity":"60%","minlevel":"36","maxlevel":"38"}],"as":[{"location":"Mirage Cave - North of Fortree","method":"Walking / Grass","rarity":"30%","minlevel":"36","maxlevel":"38"},{"location":"Mirage Cave - North of Route 124","method":"Walking / Grass","rarity":"60%","minlevel":"36","maxlevel":"38"},{"location":"Mirage Cave - West of Rustboro","method":"Walking / Grass","rarity":"60%","minlevel":"36","maxlevel":"38"}]}
