{"num":"264","x":null,"y":null,"or":[{"location":"Route 118","method":"Walking / Grass","rarity":"40%","minlevel":"21","maxlevel":"24"},{"location":"Route 118","method":"Tall Grass","rarity":"40%","minlevel":"21","maxlevel":"23"},{"location":"Route 119","method":"Tall Grass","rarity":"40%","minlevel":"22","maxlevel":"25"},{"location":"Route 120","method":"Tall Grass","rarity":"40%","minlevel":"24","maxlevel":"27"},{"location":"Route 121","method":"Walking / Grass","rarity":"30%","minlevel":"28","maxlevel":"30"},{"location":"Route 121","method":"Tall Grass","rarity":"30%","minlevel":"28","maxlevel":"30"},{"location":"Route 123","method":"Tall Grass","rarity":"30%","minlevel":"29","maxlevel":"31"}],"as":[{"location":"Route 118","method":"Walking / Grass","rarity":"40%","minlevel":"21","maxlevel":"24"},{"location":"Route 118","method":"Tall Grass","rarity":"40%","minlevel":"21","maxlevel":"23"},{"location":"Route 119","method":"Tall Grass","rarity":"40%","minlevel":"22","maxlevel":"25"},{"location":"Route 120","method":"Tall Grass","rarity":"40%","minlevel":"24","maxlevel":"27"},{"location":"Route 121","method":"Walking / Grass","rarity":"30%","minlevel":"28","maxlevel":"30"},{"location":"Route 121","method":"Tall Grass","rarity":"30%","minlevel":"28","maxlevel":"30"},{"location":"Route 123","method":"Tall Grass","rarity":"30%","minlevel":"29","maxlevel":"31"}]}
